{"data":{"site":{"siteMetadata":{"title":"Spatial Paralysis","author":"Richard Law"}},"markdownRemark":null},"pageContext":{"slug":"/cas/cas-saga/","previous":{"fields":{"slug":"/blog/cas/cas-saga/"},"frontmatter":{"title":"Crash Analysis System: The Narrative Arc","updated":null,"date":"2016-04-28T21:02:00.000Z","path":null,"tags":["open data","NZTA","NZTA CAS"]}},"next":{"fields":{"slug":"/traffic-dashboard/"},"frontmatter":{"title":"NZ Traffic Dashboard","updated":null,"date":"2017-12-31T14:25:00.000Z","path":"/blog/nz-traffic-dashboard","tags":["portfolio","development","react","JavaScript","transport","New Zealand","NZTA"]}}}}